CHANGELOG.md
CONTRIBUTING.md
LICENSE.md
MANIFEST.in
README.md
pyproject.toml
setup.cfg
setup.py
lakeshore336/Daemon.py
lakeshore336/Lakeshore336.py
lakeshore336/Monitor.py
lakeshore336/__init__.py
lakeshore336/__main__.py
lakeshore336/__project__.py
lakeshore336/lakeshore336.py
lakeshore336.egg-info/PKG-INFO
lakeshore336.egg-info/SOURCES.txt
lakeshore336.egg-info/dependency_links.txt
lakeshore336.egg-info/entry_points.txt
lakeshore336.egg-info/requires.txt
lakeshore336.egg-info/top_level.txt
lakeshore336/conf/lakeshore336.ini
lakeshore336/conf/lakeshore336_daemon.ini
lakeshore336/conf/lakeshore336_database.ini
lakeshore336/conf/lakeshore336_logging.ini