Metadata-Version: 2.1
Name: lakeshore336
Version: 0.2.0
Summary: Readout, logging and control software for the Lakeshore 336 Temperature Controller
Home-page: https://gitlab.ethz.ch/exotic-matter/cw-beam/lakeshore336
Author: Carlos Vigo
Author-email: <carlosv@phys.ethz.ch>
License: GPLv3
Platform: UNKNOWN
Classifier: Programming Language :: Python :: 3.6
Classifier: License :: OSI Approved :: GNU General Public License v3 (GPLv3)
Classifier: Operating System :: POSIX :: Linux
Classifier: Topic :: Scientific/Engineering :: Physics
Classifier: Topic :: System :: Hardware :: Hardware Drivers
Requires-Python: >=3.6
Provides-Extra: dev
Provides-Extra: docs
